setup.cfg
setup.py
shiji/__init__.py
shiji/foundation.py
shiji/urldispatch.py
shiji/webapi.py
shiji.egg-info/PKG-INFO
shiji.egg-info/SOURCES.txt
shiji.egg-info/dependency_links.txt
shiji.egg-info/entry_points.txt
shiji.egg-info/not-zip-safe
shiji.egg-info/pbr.json
shiji.egg-info/requires.txt
shiji.egg-info/top_level.txt
shiji/auth/__init__.py
shiji/auth/base_backend.py
shiji/auth/errors.py
shiji/auth/util.py
shiji/dummy_api/__init__.py
shiji/dummy_api/v1_0/__init__.py
shiji/dummy_api/v1_0/calls.py
shiji/dummy_api/v1_0/calls_list.py
shiji/dummy_api/v1_0/calls_unicode.py
shiji/i18n/__init__.py
shiji/i18n/postal_code_validator.py
shiji/stats/__init__.py
shiji/stats/vendor/__init__.py
shiji/stats/vendor/txstatsd/__init__.py
shiji/stats/vendor/txstatsd/client.py
shiji/stats/vendor/txstatsd/hashing.py
shiji/stats/vendor/txstatsd/itxstatsd.py
shiji/stats/vendor/txstatsd/process.py
shiji/stats/vendor/txstatsd/protocol.py
shiji/stats/vendor/txstatsd/report.py
shiji/stats/vendor/txstatsd/service.py
shiji/stats/vendor/txstatsd/version.py
shiji/stats/vendor/txstatsd/metrics/__init__.py
shiji/stats/vendor/txstatsd/metrics/countermetric.py
shiji/stats/vendor/txstatsd/metrics/distinctmetric.py
shiji/stats/vendor/txstatsd/metrics/extendedmetrics.py
shiji/stats/vendor/txstatsd/metrics/gaugemetric.py
shiji/stats/vendor/txstatsd/metrics/histogrammetric.py
shiji/stats/vendor/txstatsd/metrics/imetrics.py
shiji/stats/vendor/txstatsd/metrics/metermetric.py
shiji/stats/vendor/txstatsd/metrics/metric.py
shiji/stats/vendor/txstatsd/metrics/metrics.py
shiji/stats/vendor/txstatsd/metrics/slimetric.py
shiji/stats/vendor/txstatsd/metrics/timermetric.py
shiji/stats/vendor/txstatsd/server/__init__.py
shiji/stats/vendor/txstatsd/server/configurableprocessor.py
shiji/stats/vendor/txstatsd/server/httpinfo.py
shiji/stats/vendor/txstatsd/server/loggingprocessor.py
shiji/stats/vendor/txstatsd/server/processor.py
shiji/stats/vendor/txstatsd/server/protocol.py
shiji/stats/vendor/txstatsd/server/router.py
shiji/stats/vendor/txstatsd/stats/__init__.py
shiji/stats/vendor/txstatsd/stats/ewma.py
shiji/stats/vendor/txstatsd/stats/exponentiallydecayingsample.py
shiji/stats/vendor/txstatsd/stats/uniformsample.py
