Metadata-Version: 1.0
Name: shiji
Version: 1.0.15
Summary: Shiji Web API Framework
Home-page: https://github.com/williamsjj/shiji
Author: DigiTar Inc.
Author-email: support@digitar.com
License: MIT License
Keywords: rest,api,twisted,web,json,framework
Platform: UNKNOWN
